file_tree/__init__.py
file_tree/app.py
file_tree/css/app.css
file_tree/file_tree.py
file_tree/parse_tree.py
file_tree/template.py
file_tree-1.6.1.dist-info/licenses/LICENSE
file_tree-1.6.1.dist-info/WHEEL
file_tree-1.6.1.dist-info/entry_points.txt
file_tree-1.6.1.dist-info/METADATA
file_tree-1.6.1.dist-info/RECORD
