Metadata-Version: 2.4
Name: file-tree
Version: 1.6.1
Summary: Describe structure directory for visualisation and pipeline
Author: Michiel Cottaar
Author-email: Michiel Cottaar <michiel.cottaar@ndcn.ox.ac.uk>
License-Expression: MIT
License-File: LICENSE
Requires-Dist: numpy
Requires-Dist: xarray
Requires-Dist: pandas
Requires-Dist: parse
Requires-Dist: rich
Requires-Dist: textual ; extra == 'app'
Requires-Python: >=3.10
Project-URL: Changelog, https://git.fmrib.ox.ac.uk/fsl/file-tree/-/blob/main/CHANGELOG.md
Project-URL: Documentation, https://open.win.ox.ac.uk/pages/fsl/file-tree
Project-URL: Homepage, https://git.fmrib.ox.ac.uk/fsl/file-tree
Project-URL: Issues, https://git.fmrib.ox.ac.uk/fsl/file-tree/-/issues
Project-URL: Repository, https://git.fmrib.ox.ac.uk/fsl/file-tree
Provides-Extra: app
